la_election_night/__init__.py
la_election_night/ets.py
la_election_night/layouts.py
la_election_night-0.0.4.dist-info/LICENSE
la_election_night-0.0.4.dist-info/METADATA
la_election_night-0.0.4.dist-info/WHEEL
la_election_night-0.0.4.dist-info/top_level.txt
la_election_night-0.0.4.dist-info/RECORD
