Metadata-Version: 2.1
Name: la-election-night
Version: 0.0.4
Summary: Parse historical and election night result files published by the Los Angeles County Registrar-Recorder/County Clerk
Home-page: http://www.github.com/datadesk/la-election-night
Author: Los Angeles Times Data Desk
Author-email: datadesk@latimes.com
License: MIT
Platform: UNKNOWN
Classifier: Development Status :: 5 - Production/Stable
Classifier: Programming Language :: Python
Classifier: Programming Language :: Python :: 2.7
Classifier: Programming Language :: Python :: 3.4
Classifier: Programming Language :: Python :: 3.5
Classifier: Programming Language :: Python :: 3.6
Classifier: Programming Language :: Python :: 3.7
Classifier: License :: OSI Approved :: MIT License
Requires-Dist: requests
